tycho_simulation_py-0.70.0.dist-info/METADATA
tycho_simulation_py-0.70.0.dist-info/WHEEL
tycho_simulation_py/models.py
tycho_simulation_py/__init__.py
tycho_simulation_py/evm/adapter_contract.py
tycho_simulation_py/evm/token.py
tycho_simulation_py/evm/decoders.py
tycho_simulation_py/evm/constants.py
tycho_simulation_py/evm/__init__.py
tycho_simulation_py/evm/pool_state.py
tycho_simulation_py/evm/utils.py
tycho_simulation_py/evm/storage.py
tycho_simulation_py/exceptions.py
tycho_simulation_py/assets/IERC20.sol
tycho_simulation_py/assets/mocked_ERC20.sol
tycho_simulation_py/assets/ERC20.bin
tycho_simulation_py/assets/ISwapAdapter.abi
tycho_simulation_py/assets/ERC20.abi
tycho_simulation_py/_tycho_simulation_py.cpython-311-darwin.so
tycho_simulation_py-0.70.0.dist-info/RECORD
