Metadata-Version: 2.1
Name: tycho-simulation-py
Version: 0.70.0
Classifier: Programming Language :: Rust
Classifier: Programming Language :: Python :: Implementation :: CPython
Classifier: Programming Language :: Python :: Implementation :: PyPy
Requires-Dist: requests < 3
Requires-Dist: eth-abi >= 2.2.0
Requires-Dist: eth-typing >= 2.3
Requires-Dist: eth-utils >= 1.9.0
Requires-Dist: pycryptodome<4,>=3.6.6
Requires-Dist: hexbytes >= 0.2.2
Requires-Dist: tycho-indexer-client>=0.7.2
Requires-Dist: pytest; extra == 'testing'
Provides-Extra: testing
Requires-Python: >=3.7
